Metadata-Version: 2.1
Name: dewr
Version: 0.0.7
Summary: A small example package
Home-page: https://github.com/pypa/sampleproject
Author: churunmin
Author-email: churunmin@outlook.com
License: MIT
Platform: UNKNOWN
Requires-Python: >=3.6
